<?xml version="1.0" encoding="utf-8"?>
<doctrine-mapping xmlns="http://doctrine-project.org/schemas/orm/doctrine-mapping"
                  xmlns:xsi="http://www.w3.org/2001/XMLSchema-instance"
                  xsi:schemaLocation="http://doctrine-project.org/schemas/orm/doctrine-mapping http://doctrine-project.org/schemas/orm/doctrine-mapping.xsd">
    <entity name="Sulu\Bundle\SyliusConsumerBundle\Model\Product\ProductVariantInformation"
            table="pr_product_variant_informations"
            repository-class="Sulu\Bundle\SyliusConsumerBundle\Repository\Product\ProductVariantInformationRepository">
        <id name="productVariant" type="guid" association-key="true">
            <generator strategy="NONE"/>
        </id>
        <id name="dimension" type="guid" association-key="true">
            <generator strategy="NONE"/>
        </id>

        <field name="name" type="string" nullable="false"/>

        <field name="additionalData" column="additionalData" type="json"/>

        <many-to-one field="productVariant" target-entity="Sulu\Bundle\SyliusConsumerBundle\Model\Product\ProductVariant" inversed-by="productVariantInformations"/>

        <many-to-one field="dimension" target-entity="Sulu\Bundle\SyliusConsumerBundle\Model\Dimension\Dimension"/>
    </entity>
</doctrine-mapping>
